zentaxa/__init__.py
zentaxa/client.py
zentaxa/session.py
zentaxa/integrations/__init__.py
zentaxa/integrations/autogen.py
zentaxa/integrations/crewai.py
zentaxa/integrations/langchain.py
zentaxa/integrations/langgraph.py
zentaxa/integrations/llamaindex.py
zentaxa-1.1.2.dist-info/METADATA
zentaxa-1.1.2.dist-info/WHEEL
zentaxa-1.1.2.dist-info/top_level.txt
zentaxa-1.1.2.dist-info/RECORD
