Metadata-Version: 2.4
Name: zentaxa
Version: 1.1.2
Summary: Framework-agnostic observability SDK for multi-agent workflows
Author-email: zentaxa <support@zentaxa.me>
License: MIT
Project-URL: Homepage, https://github.com/zentaxa/zentaxa-sdk
Project-URL: Documentation, https://docs.zentaxa.ai
Project-URL: Repository, https://github.com/zentaxa/zentaxa-sdk
Project-URL: Issues, https://github.com/zentaxa/zentaxa-sdk/issues
Keywords: observability,llm,agents,langchain,crewai,autogen,llamaindex,monitoring
Classifier: Development Status :: 4 - Beta
Classifier: Intended Audience :: Developers
Classifier: License :: OSI Approved :: MIT License
Classifier: Programming Language :: Python :: 3
Classifier: Programming Language :: Python :: 3.8
Classifier: Programming Language :: Python :: 3.9
Classifier: Programming Language :: Python :: 3.10
Classifier: Programming Language :: Python :: 3.11
Classifier: Programming Language :: Python :: 3.12
Classifier: Topic :: Software Development :: Libraries :: Python Modules
Classifier: Topic :: System :: Monitoring
Requires-Python: >=3.8
Requires-Dist: httpx>=0.27.0
Provides-Extra: langchain
Requires-Dist: langchain>=0.1.0; extra == "langchain"
Provides-Extra: crewai
Requires-Dist: crewai>=0.1.0; extra == "crewai"
Provides-Extra: autogen
Requires-Dist: pyautogen>=0.2.0; extra == "autogen"
Provides-Extra: llamaindex
Requires-Dist: llama-index>=0.10.0; extra == "llamaindex"
Provides-Extra: all
Requires-Dist: langchain>=0.1.0; extra == "all"
Requires-Dist: crewai>=0.1.0; extra == "all"
Requires-Dist: pyautogen>=0.2.0; extra == "all"
Requires-Dist: llama-index>=0.10.0; extra == "all"
Provides-Extra: dev
Requires-Dist: pytest>=7.0.0; extra == "dev"
Requires-Dist: pytest-asyncio>=0.21.0; extra == "dev"
Requires-Dist: black>=23.0.0; extra == "dev"
Requires-Dist: mypy>=1.0.0; extra == "dev"
